toknc/__init__.py
toknc/cli.py
toknc-0.1.1.dist-info/licenses/LICENSE
toknc-0.1.1.dist-info/METADATA
toknc-0.1.1.dist-info/WHEEL
toknc-0.1.1.dist-info/entry_points.txt
toknc-0.1.1.dist-info/top_level.txt
toknc-0.1.1.dist-info/RECORD
