Metadata-Version: 2.4
Name: toknc
Version: 0.1.1
Summary: A Python CLI application that estimates token usage for files in a directory
Author-email: gato001k1 <eduardoaltri520@gmail.com>
License: MIT
Project-URL: Homepage, https://github.com/gato001k1/toknc
Project-URL: Repository, https://github.com/gato001k1/toknc
Project-URL: Documentation, https://github.com/gato001k1/toknc#readme
Project-URL: Issues, https://github.com/gato001k1/toknc/issues
Keywords: token,gpt,openai,cli,code-analysis
Classifier: Development Status :: 4 - Beta
Classifier: Intended Audience :: Developers
Classifier: Topic :: Software Development :: Code Generators
Classifier: License :: OSI Approved :: MIT License
Classifier: Programming Language :: Python :: 3
Classifier: Programming Language :: Python :: 3.7
Classifier: Programming Language :: Python :: 3.8
Classifier: Programming Language :: Python :: 3.9
Classifier: Programming Language :: Python :: 3.10
Classifier: Programming Language :: Python :: 3.11
Classifier: Programming Language :: Python :: 3.12
Requires-Python: >=3.7
License-File: LICENSE
Provides-Extra: tiktoken
Requires-Dist: tiktoken>=0.5.0; extra == "tiktoken"
Dynamic: license-file
